rom/__init__.py
rom/rom.py
rom/test_roman_numerals.py
gnboorse_rom-0.0.1.dist-info/LICENSE
gnboorse_rom-0.0.1.dist-info/METADATA
gnboorse_rom-0.0.1.dist-info/WHEEL
gnboorse_rom-0.0.1.dist-info/top_level.txt
gnboorse_rom-0.0.1.dist-info/RECORD
