Metadata-Version: 2.1
Name: gnboorse-rom
Version: 0.0.1
Summary: Python Roman Numeral Parsing
Home-page: https://github.com/gnboorse/rom
Author: Gabriel Boorse
Author-email: gnboorse@gmail.com
License: UNKNOWN
Platform: UNKNOWN
Classifier: Programming Language :: Python :: 3
Classifier: License :: OSI Approved :: Apache Software License
Classifier: Development Status :: 2 - Pre-Alpha
Classifier: Operating System :: OS Independent
Classifier: Topic :: Scientific/Engineering :: Mathematics
Requires-Python: >=3.6
